quantium_signal/__init__.py
quantium_signal/signal.py
quantium_signal-0.1.0b0.dist-info/LICENSE
quantium_signal-0.1.0b0.dist-info/METADATA
quantium_signal-0.1.0b0.dist-info/WHEEL
quantium_signal-0.1.0b0.dist-info/top_level.txt
quantium_signal-0.1.0b0.dist-info/RECORD
