Metadata-Version: 2.2
Name: quantium-signal
Version: 0.1.0b0
Summary: Unlock TradingView alerts without the premium plan using Quantium Signal.
Author: Artyom Vancyan
Author-email: artyom.vancyan2000@gmail.com
License: MIT
Project-URL: Source Code, https://github.com/quantium-ai/signal/
Keywords: okx,free,bybit,signal,crypto,pionex,binance,tradingview
Platform: unix
Platform: linux
Platform: osx
Platform: win32
Classifier: Operating System :: OS Independent
Classifier: Development Status :: 4 - Beta
Classifier: Programming Language :: Python
Classifier: Programming Language :: Python :: 3
Classifier: Programming Language :: Python :: 3.8
Classifier: Programming Language :: Python :: 3.9
Classifier: Programming Language :: Python :: 3.10
Classifier: Programming Language :: Python :: 3.11
Classifier: Programming Language :: Python :: 3.12
Classifier: License :: OSI Approved :: MIT License
Requires-Python: >=3.8
License-File: LICENSE
Requires-Dist: aiosmtpd>=1.4.6
Requires-Dist: cloudscraper>=1.2.71
